.gitignore
LICENCE.txt
README.md
environment.yml
pyproject.toml
setup.py
.github/workflows/conda-build.yaml
.github/workflows/pipy-publish.yaml
conda-recipe/meta.yaml
zerospeech_libriabx2.egg-info/PKG-INFO
zerospeech_libriabx2.egg-info/SOURCES.txt
zerospeech_libriabx2.egg-info/dependency_links.txt
zerospeech_libriabx2.egg-info/entry_points.txt
zerospeech_libriabx2.egg-info/not-zip-safe
zerospeech_libriabx2.egg-info/requires.txt
zerospeech_libriabx2.egg-info/top_level.txt
zrc_abx2/__init__.py
zrc_abx2/eval_ABX.py
zrc_abx2/ABX_src/__init__.py
zrc_abx2/ABX_src/abx_group_computation.py
zrc_abx2/ABX_src/dtw.c
zrc_abx2/ABX_src/dtw.pyx
zrc_abx2/ABX_src/models.py
zrc_abx2/ABX_src/ABXDataset/abx_feature_dataset.py
zrc_abx2/ABX_src/ABXDataset/abx_feature_loader.py
zrc_abx2/ABX_src/ABXDataset/abx_item_file_loader.py
zrc_abx2/ABX_src/ABXIterators/abx_iterator_factory.py
zrc_abx2/ABX_src/ABXIterators/abx_iterators.py
zrc_abx2/ABX_src/ABXIterators/abx_iterators_anycontext.py
zrc_abx2/cpc/LICENSE
zrc_abx2/cpc/README.md
zrc_abx2/cpc/__init__.py
zrc_abx2/cpc/cpc_default_config.py
zrc_abx2/cpc/dataset.py
zrc_abx2/cpc/feature_loader.py
zrc_abx2/cpc/model.py
zrc_abx2/cpc/train.py
zrc_abx2/cpc/transformers.py
zrc_abx2/cpc/criterion/__init__.py
zrc_abx2/cpc/criterion/criterion.py
zrc_abx2/cpc/criterion/custom_layers.py
zrc_abx2/cpc/criterion/seq_alignment.py
zrc_abx2/cpc/utils/__init__.py
zrc_abx2/cpc/utils/misc.py
zrc_abx2/cpc/utils/unit_tests.py