Metadata-Version: 2.1
Name: zerospeech-libriabx2
Version: 0.9.8
Summary: Package implementing a revamped method to the librilight-abx.
Author-email: Mark Hallap <mark.hallap@mail.utoronto.ca>, CoML Team <dev@zerospeech.com>, Nicolas Hamilakis <nicolas.hamilakis@ens.psl.eu>
Project-URL: documentation, https://zerospeech.com/toolbox/
Project-URL: homepage, https://zerospeech.com/
Project-URL: repository, https://github.com/zerospeech/libri-light-abx2
Keywords: speech,machine-learning,challenges,research-tool,benchmark-speech,zerospeech
Classifier: Programming Language :: Python :: 3.8
Classifier: Programming Language :: Python :: 3.9
Classifier: Programming Language :: Python :: 3.10
Classifier: Programming Language :: Python :: 3.11
Classifier: Topic :: Scientific/Engineering :: Artificial Intelligence
Classifier: Intended Audience :: Science/Research
Requires-Python: >=3.8
License-File: LICENCE.txt
